Metadata-Version: 2.1
Name: hdfs-pycompss
Version: 0.3
Summary: HDFSPyCOMPSs is an API that enables PyCOMPSs to read HDFS files in parallel.
Home-page: https://github.com/eubr-bigsea/compss-hdfs
Author: Lucas Miguel Ponce
Author-email: lucasmsp@dcc.ufmg.br
License: Apache License, Version 2.0
Platform: Linux
Classifier: Programming Language :: Python :: 3
Classifier: Programming Language :: Python :: 3.6
Classifier: License :: OSI Approved :: Apache Software License
Classifier: Operating System :: POSIX :: Linux
Classifier: Topic :: Software Development :: Libraries
Classifier: Topic :: Software Development :: Libraries :: Python Modules
Classifier: Topic :: System :: Distributed Computing
